LICENSE
README.md
setup.py
pyjs8call/__init__.py
pyjs8call/__main__.py
pyjs8call/appmonitor.py
pyjs8call/callbacks.py
pyjs8call/client.py
pyjs8call/confighandler.py
pyjs8call/hbnetwork.py
pyjs8call/inboxmonitor.py
pyjs8call/js8call.py
pyjs8call/message.py
pyjs8call/notifications.py
pyjs8call/offsetmonitor.py
pyjs8call/outgoingmonitor.py
pyjs8call/propagation.py
pyjs8call/schedulemonitor.py
pyjs8call/settings.py
pyjs8call/spotmonitor.py
pyjs8call/timemonitor.py
pyjs8call/windowmonitor.py
pyjs8call.egg-info/PKG-INFO
pyjs8call.egg-info/SOURCES.txt
pyjs8call.egg-info/dependency_links.txt
pyjs8call.egg-info/requires.txt
pyjs8call.egg-info/top_level.txt
tests/test_cross_platform.py
tests/test_helpers.py
tests/test_start.py