Metadata-Version: 2.1
Name: pyjs8call
Version: 0.2.3
Summary: Python package for interfacing with the JS8Call API
Home-page: https://github.com/simplyequipped/pyjs8call
Author: Simply Equipped LLC
Author-email: howard@simplyequipped.com
Classifier: Programming Language :: Python :: 3
Classifier: License :: OSI Approved :: MIT License
Classifier: Operating System :: POSIX :: Linux
Classifier: Operating System :: MacOS :: MacOS X
Classifier: Operating System :: Microsoft :: Windows
Requires-Python: >=3.6.1
License-File: LICENSE
Requires-Dist: psutil>=5.3
